{"website": "", "council_district": "37", "neighborhood": "East New York", "description": "This garden has food, flowers, fruit, a baseball field, and a place for our children to play", "private events": ["members and non-members", "reservation & rental fee", "reservation only", "yes"], "waitlist": "no", "food": {"herbs": ["basil", "chive", "dill", "lavender", "mint", "parsley", "sage", "thyme"], "vegetables": ["beans", "beet", "broccoli", "cabbage", "carrot", "cauliflower", "cayenne", "celery", "corn", "cucumber", "eggplant", "garlic", "jalape\u00f1o", "onion", "parsnip", "peas", "scallion", "summer squash", "sweet peppers", "tomato", "turnip", "winter squash"], "trees": ["4 apple", "1 apricot", "4 cherry", "2 peach", "1 pear"], "greens": ["chard", "collard", "kale", "lettuce", "spinach"], "fruits": ["blackberry", "blueberry", "grape", "raspberry", "strawberry", "watermelon"]}, "food use": ["donated", "used by growers"], "community_board": "5", "who composts": "garden members only", "other_plants": ["native plant garden", "shade trees", "shrubs"], "ownership": "NYC Dept. of Parks & Recreation", "address": "143-151 Fountain Avenue", "composts currently": "yes", "languages_spoken": "english, spanish", "borough": "Brooklyn", "id": "823", "year_started": "1994", "art": [], "name": "Green Gems", "open hours": "", "structures": ["greenhouse or hoop house", "grill", "playground", "seating area"], "previous_use": " vacant lot ", "works with schools": "no", "dues": "no", "perceived edibility": "26-50%", "surveyed": true, "water features": ["water pump"], "volunteers needed": "yes", "fences": "chain link", "events": ["barbecues", "concerts", "performance", "picnics"]}